{
  "metadata": {
    "version": "2.0",
    "created_at": "2026-01-10",
    "updated_at": "2026-01-12",
    "description": "Major 345kV and 138kV transmission lines in the Texas (ERCOT) Interconnection",
    "data_sources": ["HIFLD", "ERCOT transmission planning documents", "Public utility filings", "ERCOT CREZ project documentation"],
    "coverage": "ERCOT region - comprehensive transmission network including CREZ lines",
    "notes": "Phase B - Expanded with CREZ corridors, backbone 345kV triangle, coastal connections, and Panhandle wind integration. Capacity estimates based on voltage level and typical ERCOT line ratings."
  },
  "branches": [
    {
      "id": "branch-wa-parish-hiram-clarke",
      "name": "W.A. Parish - Hiram Clarke",
      "from_node_id": "node-houston-w-a-parish",
      "to_node_id": "node-houston-hiram-clarke",
      "voltage_kv": 345,
      "capacity_mw": 1200,
      "length_km": 35,
      "status": "operational",
      "is_hvdc": false,
      "owner": "CenterPoint Energy",
      "data_source": "HIFLD"
    },
    {
      "id": "branch-hiram-clarke-polk",
      "name": "Hiram Clarke - Polk",
      "from_node_id": "node-houston-hiram-clarke",
      "to_node_id": "node-houston-polk",
      "voltage_kv": 345,
      "capacity_mw": 1200,
      "length_km": 18,
      "status": "operational",
      "is_hvdc": false,
      "owner": "CenterPoint Energy",
      "data_source": "HIFLD"
    },
    {
      "id": "branch-polk-greens-bayou",
      "name": "Polk - Greens Bayou",
      "from_node_id": "node-houston-polk",
      "to_node_id": "node-houston-greens-bayou",
      "voltage_kv": 345,
      "capacity_mw": 1200,
      "length_km": 25,
      "status": "operational",
      "is_hvdc": false,
      "owner": "CenterPoint Energy",
      "data_source": "HIFLD"
    },
    {
      "id": "branch-greens-bayou-cedar-bayou",
      "name": "Greens Bayou - Cedar Bayou",
      "from_node_id": "node-houston-greens-bayou",
      "to_node_id": "node-houston-cedar-bayou",
      "voltage_kv": 345,
      "capacity_mw": 1200,
      "length_km": 32,
      "status": "operational",
      "is_hvdc": false,
      "owner": "CenterPoint Energy",
      "data_source": "HIFLD"
    },
    {
      "id": "branch-houston-nw-katy",
      "name": "Houston Northwest - Katy",
      "from_node_id": "node-houston-northwest",
      "to_node_id": "node-houston-katy",
      "voltage_kv": 345,
      "capacity_mw": 1200,
      "length_km": 28,
      "status": "operational",
      "is_hvdc": false,
      "owner": "CenterPoint Energy",
      "data_source": "HIFLD"
    },
    {
      "id": "branch-katy-wa-parish",
      "name": "Katy - W.A. Parish",
      "from_node_id": "node-houston-katy",
      "to_node_id": "node-houston-w-a-parish",
      "voltage_kv": 345,
      "capacity_mw": 1200,
      "length_km": 25,
      "status": "operational",
      "is_hvdc": false,
      "owner": "CenterPoint Energy",
      "data_source": "HIFLD"
    },
    {
      "id": "branch-wa-parish-sugarland",
      "name": "W.A. Parish - Sugar Land",
      "from_node_id": "node-houston-w-a-parish",
      "to_node_id": "node-houston-sugarland",
      "voltage_kv": 345,
      "capacity_mw": 1200,
      "length_km": 12,
      "status": "operational",
      "is_hvdc": false,
      "owner": "CenterPoint Energy",
      "data_source": "HIFLD"
    },
    {
      "id": "branch-cedar-bayou-baytown",
      "name": "Cedar Bayou - Baytown",
      "from_node_id": "node-houston-cedar-bayou",
      "to_node_id": "node-coastal-baytown",
      "voltage_kv": 345,
      "capacity_mw": 1200,
      "length_km": 8,
      "status": "operational",
      "is_hvdc": false,
      "owner": "CenterPoint Energy",
      "data_source": "HIFLD"
    },
    {
      "id": "branch-baytown-texas-city",
      "name": "Baytown - Texas City",
      "from_node_id": "node-coastal-baytown",
      "to_node_id": "node-coastal-texas-city",
      "voltage_kv": 345,
      "capacity_mw": 1000,
      "length_km": 42,
      "status": "operational",
      "is_hvdc": false,
      "owner": "CenterPoint Energy",
      "data_source": "HIFLD"
    },
    {
      "id": "branch-comanche-peak-midlothian",
      "name": "Comanche Peak - Midlothian",
      "from_node_id": "node-nuclear-comanche-peak",
      "to_node_id": "node-dfw-midlothian",
      "voltage_kv": 345,
      "capacity_mw": 1500,
      "length_km": 72,
      "status": "operational",
      "is_hvdc": false,
      "owner": "Oncor Electric",
      "data_source": "HIFLD"
    },
    {
      "id": "branch-midlothian-grandview",
      "name": "Midlothian - Grandview",
      "from_node_id": "node-dfw-midlothian",
      "to_node_id": "node-grandview",
      "voltage_kv": 345,
      "capacity_mw": 1200,
      "length_km": 25,
      "status": "operational",
      "is_hvdc": false,
      "owner": "Oncor Electric",
      "data_source": "HIFLD"
    },
    {
      "id": "branch-midlothian-parkdale",
      "name": "Midlothian - Parkdale",
      "from_node_id": "node-dfw-midlothian",
      "to_node_id": "node-dfw-parkdale",
      "voltage_kv": 345,
      "capacity_mw": 1200,
      "length_km": 42,
      "status": "operational",
      "is_hvdc": false,
      "owner": "Oncor Electric",
      "data_source": "HIFLD"
    },
    {
      "id": "branch-parkdale-forney",
      "name": "Parkdale - Forney",
      "from_node_id": "node-dfw-parkdale",
      "to_node_id": "node-dfw-forney",
      "voltage_kv": 345,
      "capacity_mw": 1200,
      "length_km": 38,
      "status": "operational",
      "is_hvdc": false,
      "owner": "Oncor Electric",
      "data_source": "HIFLD"
    },
    {
      "id": "branch-parkdale-trinity",
      "name": "Parkdale - Trinity",
      "from_node_id": "node-dfw-parkdale",
      "to_node_id": "node-dfw-trinity",
      "voltage_kv": 345,
      "capacity_mw": 1200,
      "length_km": 32,
      "status": "operational",
      "is_hvdc": false,
      "owner": "Oncor Electric",
      "data_source": "HIFLD"
    },
    {
      "id": "branch-trinity-handley",
      "name": "Trinity - Handley",
      "from_node_id": "node-dfw-trinity",
      "to_node_id": "node-dfw-handley",
      "voltage_kv": 345,
      "capacity_mw": 1200,
      "length_km": 15,
      "status": "operational",
      "is_hvdc": false,
      "owner": "Oncor Electric",
      "data_source": "HIFLD"
    },
    {
      "id": "branch-handley-eagle-mountain",
      "name": "Handley - Eagle Mountain",
      "from_node_id": "node-dfw-handley",
      "to_node_id": "node-dfw-eagle-mountain",
      "voltage_kv": 345,
      "capacity_mw": 1200,
      "length_km": 32,
      "status": "operational",
      "is_hvdc": false,
      "owner": "Oncor Electric",
      "data_source": "HIFLD"
    },
    {
      "id": "branch-north-texas-anna",
      "name": "North Texas - Anna",
      "from_node_id": "node-dfw-north-texas",
      "to_node_id": "node-dfw-anna",
      "voltage_kv": 345,
      "capacity_mw": 1200,
      "length_km": 38,
      "status": "operational",
      "is_hvdc": false,
      "owner": "Oncor Electric",
      "data_source": "HIFLD"
    },
    {
      "id": "branch-anna-panda-sherman",
      "name": "Anna - Panda Sherman",
      "from_node_id": "node-dfw-anna",
      "to_node_id": "node-panda-sherman",
      "voltage_kv": 345,
      "capacity_mw": 1200,
      "length_km": 35,
      "status": "operational",
      "is_hvdc": false,
      "owner": "Oncor Electric",
      "data_source": "HIFLD"
    },
    {
      "id": "branch-forney-martin-lake",
      "name": "Forney - Martin Lake",
      "from_node_id": "node-dfw-forney",
      "to_node_id": "node-dfw-martin-lake",
      "voltage_kv": 345,
      "capacity_mw": 1500,
      "length_km": 175,
      "status": "operational",
      "is_hvdc": false,
      "owner": "Oncor Electric",
      "data_source": "HIFLD"
    },
    {
      "id": "branch-martin-lake-monticello",
      "name": "Martin Lake - Monticello",
      "from_node_id": "node-dfw-martin-lake",
      "to_node_id": "node-monticello",
      "voltage_kv": 345,
      "capacity_mw": 1500,
      "length_km": 95,
      "status": "operational",
      "is_hvdc": false,
      "owner": "Oncor Electric",
      "data_source": "HIFLD"
    },
    {
      "id": "branch-monticello-welsh",
      "name": "Monticello - Welsh",
      "from_node_id": "node-monticello",
      "to_node_id": "node-welsh",
      "voltage_kv": 345,
      "capacity_mw": 1500,
      "length_km": 18,
      "status": "operational",
      "is_hvdc": false,
      "owner": "AEP Texas",
      "data_source": "HIFLD"
    },
    {
      "id": "branch-welsh-pirkey",
      "name": "Welsh - Pirkey",
      "from_node_id": "node-welsh",
      "to_node_id": "node-pirkey",
      "voltage_kv": 345,
      "capacity_mw": 1200,
      "length_km": 68,
      "status": "operational",
      "is_hvdc": false,
      "owner": "AEP SWEPCO",
      "data_source": "HIFLD"
    },
    {
      "id": "branch-spruce-braunig",
      "name": "Spruce - Braunig",
      "from_node_id": "node-san-antonio-spruce",
      "to_node_id": "node-san-antonio-braunig",
      "voltage_kv": 345,
      "capacity_mw": 1200,
      "length_km": 8,
      "status": "operational",
      "is_hvdc": false,
      "owner": "CPS Energy",
      "data_source": "HIFLD"
    },
    {
      "id": "branch-braunig-calaveras",
      "name": "Braunig - Calaveras",
      "from_node_id": "node-san-antonio-braunig",
      "to_node_id": "node-san-antonio-calaveras",
      "voltage_kv": 345,
      "capacity_mw": 1200,
      "length_km": 6,
      "status": "operational",
      "is_hvdc": false,
      "owner": "CPS Energy",
      "data_source": "HIFLD"
    },
    {
      "id": "branch-spruce-tesoro",
      "name": "Spruce - Tesoro",
      "from_node_id": "node-san-antonio-spruce",
      "to_node_id": "node-san-antonio-tesoro",
      "voltage_kv": 345,
      "capacity_mw": 1200,
      "length_km": 18,
      "status": "operational",
      "is_hvdc": false,
      "owner": "CPS Energy",
      "data_source": "HIFLD"
    },
    {
      "id": "branch-tesoro-cagnon",
      "name": "Tesoro - Cagnon",
      "from_node_id": "node-san-antonio-tesoro",
      "to_node_id": "node-san-antonio-cagnon",
      "voltage_kv": 345,
      "capacity_mw": 1200,
      "length_km": 22,
      "status": "operational",
      "is_hvdc": false,
      "owner": "CPS Energy",
      "data_source": "HIFLD"
    },
    {
      "id": "branch-tesoro-new-braunfels",
      "name": "Tesoro - New Braunfels",
      "from_node_id": "node-san-antonio-tesoro",
      "to_node_id": "node-new-braunfels",
      "voltage_kv": 345,
      "capacity_mw": 1200,
      "length_km": 45,
      "status": "operational",
      "is_hvdc": false,
      "owner": "CPS Energy",
      "data_source": "HIFLD"
    },
    {
      "id": "branch-new-braunfels-seguin",
      "name": "New Braunfels - Seguin",
      "from_node_id": "node-new-braunfels",
      "to_node_id": "node-seguin",
      "voltage_kv": 345,
      "capacity_mw": 1000,
      "length_km": 22,
      "status": "operational",
      "is_hvdc": false,
      "owner": "CPS Energy",
      "data_source": "HIFLD"
    },
    {
      "id": "branch-new-braunfels-san-marcos",
      "name": "New Braunfels - San Marcos",
      "from_node_id": "node-new-braunfels",
      "to_node_id": "node-san-marcos",
      "voltage_kv": 345,
      "capacity_mw": 1000,
      "length_km": 25,
      "status": "operational",
      "is_hvdc": false,
      "owner": "Oncor Electric",
      "data_source": "HIFLD"
    },
    {
      "id": "branch-san-marcos-hays",
      "name": "San Marcos - Hays",
      "from_node_id": "node-san-marcos",
      "to_node_id": "node-hays",
      "voltage_kv": 345,
      "capacity_mw": 1000,
      "length_km": 18,
      "status": "operational",
      "is_hvdc": false,
      "owner": "Oncor Electric",
      "data_source": "HIFLD"
    },
    {
      "id": "branch-hays-austin-south",
      "name": "Hays - Austin South",
      "from_node_id": "node-hays",
      "to_node_id": "node-austin-south",
      "voltage_kv": 345,
      "capacity_mw": 1000,
      "length_km": 22,
      "status": "operational",
      "is_hvdc": false,
      "owner": "Austin Energy",
      "data_source": "HIFLD"
    },
    {
      "id": "branch-austin-south-decker",
      "name": "Austin South - Decker Creek",
      "from_node_id": "node-austin-south",
      "to_node_id": "node-austin-decker",
      "voltage_kv": 345,
      "capacity_mw": 1200,
      "length_km": 18,
      "status": "operational",
      "is_hvdc": false,
      "owner": "Austin Energy",
      "data_source": "HIFLD"
    },
    {
      "id": "branch-decker-sand-hill",
      "name": "Decker Creek - Sand Hill",
      "from_node_id": "node-austin-decker",
      "to_node_id": "node-austin-sand-hill",
      "voltage_kv": 345,
      "capacity_mw": 1000,
      "length_km": 10,
      "status": "operational",
      "is_hvdc": false,
      "owner": "Austin Energy",
      "data_source": "HIFLD"
    },
    {
      "id": "branch-decker-sim-gideon",
      "name": "Decker Creek - Sim Gideon",
      "from_node_id": "node-austin-decker",
      "to_node_id": "node-sim-gideon",
      "voltage_kv": 345,
      "capacity_mw": 1000,
      "length_km": 18,
      "status": "operational",
      "is_hvdc": false,
      "owner": "LCRA",
      "data_source": "HIFLD"
    },
    {
      "id": "branch-sim-gideon-lost-pines",
      "name": "Sim Gideon - Lost Pines",
      "from_node_id": "node-sim-gideon",
      "to_node_id": "node-lost-pines",
      "voltage_kv": 345,
      "capacity_mw": 1000,
      "length_km": 15,
      "status": "operational",
      "is_hvdc": false,
      "owner": "LCRA",
      "data_source": "HIFLD"
    },
    {
      "id": "branch-fayette-singleton",
      "name": "Fayette - Singleton",
      "from_node_id": "node-austin-fayette",
      "to_node_id": "node-singleton",
      "voltage_kv": 345,
      "capacity_mw": 1200,
      "length_km": 95,
      "status": "operational",
      "is_hvdc": false,
      "owner": "LCRA / CenterPoint",
      "data_source": "HIFLD"
    },
    {
      "id": "branch-singleton-wa-parish",
      "name": "Singleton - W.A. Parish",
      "from_node_id": "node-singleton",
      "to_node_id": "node-houston-w-a-parish",
      "voltage_kv": 345,
      "capacity_mw": 1200,
      "length_km": 68,
      "status": "operational",
      "is_hvdc": false,
      "owner": "CenterPoint Energy",
      "data_source": "HIFLD"
    },
    {
      "id": "branch-sweetwater-sub-roscoe",
      "name": "Sweetwater - Roscoe",
      "from_node_id": "node-west-texas-sweetwater-sub",
      "to_node_id": "node-wind-roscoe",
      "voltage_kv": 345,
      "capacity_mw": 1500,
      "length_km": 15,
      "status": "operational",
      "is_hvdc": false,
      "owner": "Oncor Electric",
      "data_source": "HIFLD"
    },
    {
      "id": "branch-sweetwater-sub-horse-hollow",
      "name": "Sweetwater - Horse Hollow",
      "from_node_id": "node-west-texas-sweetwater-sub",
      "to_node_id": "node-wind-horse-hollow",
      "voltage_kv": 345,
      "capacity_mw": 1500,
      "length_km": 32,
      "status": "operational",
      "is_hvdc": false,
      "owner": "Oncor Electric",
      "data_source": "HIFLD"
    },
    {
      "id": "branch-sweetwater-sub-colorado-city",
      "name": "Sweetwater - Colorado City",
      "from_node_id": "node-west-texas-sweetwater-sub",
      "to_node_id": "node-west-texas-colorado-city",
      "voltage_kv": 345,
      "capacity_mw": 1500,
      "length_km": 42,
      "status": "operational",
      "is_hvdc": false,
      "owner": "Oncor Electric",
      "data_source": "HIFLD"
    },
    {
      "id": "branch-colorado-city-big-spring",
      "name": "Colorado City - Big Spring",
      "from_node_id": "node-west-texas-colorado-city",
      "to_node_id": "node-west-texas-big-spring",
      "voltage_kv": 345,
      "capacity_mw": 1500,
      "length_km": 58,
      "status": "operational",
      "is_hvdc": false,
      "owner": "Oncor Electric",
      "data_source": "HIFLD"
    },
    {
      "id": "branch-big-spring-midland",
      "name": "Big Spring - Midland",
      "from_node_id": "node-west-texas-big-spring",
      "to_node_id": "node-west-texas-midland",
      "voltage_kv": 345,
      "capacity_mw": 1500,
      "length_km": 62,
      "status": "operational",
      "is_hvdc": false,
      "owner": "Oncor Electric",
      "data_source": "HIFLD"
    },
    {
      "id": "branch-midland-odessa",
      "name": "Midland - Odessa",
      "from_node_id": "node-west-texas-midland",
      "to_node_id": "node-west-texas-odessa",
      "voltage_kv": 345,
      "capacity_mw": 1500,
      "length_km": 32,
      "status": "operational",
      "is_hvdc": false,
      "owner": "Oncor Electric",
      "data_source": "HIFLD"
    },
    {
      "id": "branch-odessa-notrees",
      "name": "Odessa - Notrees",
      "from_node_id": "node-west-texas-odessa",
      "to_node_id": "node-wind-notrees",
      "voltage_kv": 345,
      "capacity_mw": 1200,
      "length_km": 38,
      "status": "operational",
      "is_hvdc": false,
      "owner": "Oncor Electric",
      "data_source": "HIFLD"
    },
    {
      "id": "branch-midland-permian-basin",
      "name": "Midland - Permian Basin",
      "from_node_id": "node-west-texas-midland",
      "to_node_id": "node-permian-basin",
      "voltage_kv": 345,
      "capacity_mw": 1500,
      "length_km": 55,
      "status": "operational",
      "is_hvdc": false,
      "owner": "Oncor Electric",
      "data_source": "HIFLD"
    },
    {
      "id": "branch-permian-king-mountain",
      "name": "Permian Basin - King Mountain",
      "from_node_id": "node-permian-basin",
      "to_node_id": "node-wind-king-mountain",
      "voltage_kv": 345,
      "capacity_mw": 1200,
      "length_km": 68,
      "status": "operational",
      "is_hvdc": false,
      "owner": "Oncor Electric",
      "data_source": "HIFLD"
    },
    {
      "id": "branch-sweetwater-sub-jones-county",
      "name": "Sweetwater - Jones County",
      "from_node_id": "node-west-texas-sweetwater-sub",
      "to_node_id": "node-west-texas-jones-county",
      "voltage_kv": 345,
      "capacity_mw": 1500,
      "length_km": 58,
      "status": "operational",
      "is_hvdc": false,
      "owner": "Oncor Electric",
      "data_source": "HIFLD"
    },
    {
      "id": "branch-jones-county-fluvanna",
      "name": "Jones County - Fluvanna",
      "from_node_id": "node-west-texas-jones-county",
      "to_node_id": "node-wind-fluvanna",
      "voltage_kv": 345,
      "capacity_mw": 1200,
      "length_km": 125,
      "status": "operational",
      "is_hvdc": false,
      "owner": "Oncor Electric",
      "data_source": "HIFLD"
    },
    {
      "id": "branch-fluvanna-lubbock",
      "name": "Fluvanna - Lubbock",
      "from_node_id": "node-wind-fluvanna",
      "to_node_id": "node-west-texas-lubbock",
      "voltage_kv": 345,
      "capacity_mw": 1200,
      "length_km": 95,
      "status": "operational",
      "is_hvdc": false,
      "owner": "Xcel Energy / Oncor",
      "data_source": "HIFLD"
    },
    {
      "id": "branch-lubbock-panhandle-1",
      "name": "Lubbock - Panhandle Wind 1",
      "from_node_id": "node-west-texas-lubbock",
      "to_node_id": "node-wind-panhandle-1",
      "voltage_kv": 345,
      "capacity_mw": 1200,
      "length_km": 185,
      "status": "operational",
      "is_hvdc": false,
      "owner": "Xcel Energy",
      "data_source": "HIFLD"
    },
    {
      "id": "branch-stp-victoria",
      "name": "South Texas Project - Victoria",
      "from_node_id": "node-nuclear-south-texas-project",
      "to_node_id": "node-south-texas-victoria",
      "voltage_kv": 345,
      "capacity_mw": 1800,
      "length_km": 85,
      "status": "operational",
      "is_hvdc": false,
      "owner": "AEP Texas",
      "data_source": "HIFLD"
    },
    {
      "id": "branch-stp-freeport",
      "name": "South Texas Project - Freeport",
      "from_node_id": "node-nuclear-south-texas-project",
      "to_node_id": "node-coastal-freeport",
      "voltage_kv": 345,
      "capacity_mw": 1500,
      "length_km": 72,
      "status": "operational",
      "is_hvdc": false,
      "owner": "CenterPoint Energy",
      "data_source": "HIFLD"
    },
    {
      "id": "branch-freeport-wa-parish",
      "name": "Freeport - W.A. Parish",
      "from_node_id": "node-coastal-freeport",
      "to_node_id": "node-houston-w-a-parish",
      "voltage_kv": 345,
      "capacity_mw": 1200,
      "length_km": 65,
      "status": "operational",
      "is_hvdc": false,
      "owner": "CenterPoint Energy",
      "data_source": "HIFLD"
    },
    {
      "id": "branch-victoria-coleto-creek",
      "name": "Victoria - Coleto Creek",
      "from_node_id": "node-south-texas-victoria",
      "to_node_id": "node-coastal-coleto-creek",
      "voltage_kv": 345,
      "capacity_mw": 1200,
      "length_km": 25,
      "status": "operational",
      "is_hvdc": false,
      "owner": "AEP Texas",
      "data_source": "HIFLD"
    },
    {
      "id": "branch-coleto-creek-san-patricio",
      "name": "Coleto Creek - San Patricio",
      "from_node_id": "node-coastal-coleto-creek",
      "to_node_id": "node-coastal-san-patricio",
      "voltage_kv": 345,
      "capacity_mw": 1200,
      "length_km": 82,
      "status": "operational",
      "is_hvdc": false,
      "owner": "AEP Texas",
      "data_source": "HIFLD"
    },
    {
      "id": "branch-san-patricio-corpus-christi",
      "name": "San Patricio - Corpus Christi",
      "from_node_id": "node-coastal-san-patricio",
      "to_node_id": "node-south-texas-corpus-christi",
      "voltage_kv": 345,
      "capacity_mw": 1000,
      "length_km": 32,
      "status": "operational",
      "is_hvdc": false,
      "owner": "AEP Texas",
      "data_source": "HIFLD"
    },
    {
      "id": "branch-corpus-nueces-bay",
      "name": "Corpus Christi - Nueces Bay",
      "from_node_id": "node-south-texas-corpus-christi",
      "to_node_id": "node-coastal-nueces-bay",
      "voltage_kv": 345,
      "capacity_mw": 800,
      "length_km": 12,
      "status": "operational",
      "is_hvdc": false,
      "owner": "AEP Texas",
      "data_source": "HIFLD"
    },
    {
      "id": "branch-corpus-barney-davis",
      "name": "Corpus Christi - Barney Davis",
      "from_node_id": "node-south-texas-corpus-christi",
      "to_node_id": "node-barney-davis",
      "voltage_kv": 345,
      "capacity_mw": 800,
      "length_km": 25,
      "status": "operational",
      "is_hvdc": false,
      "owner": "AEP Texas",
      "data_source": "HIFLD"
    },
    {
      "id": "branch-corpus-harlingen",
      "name": "Corpus Christi - Harlingen",
      "from_node_id": "node-south-texas-corpus-christi",
      "to_node_id": "node-south-texas-harlingen",
      "voltage_kv": 138,
      "capacity_mw": 400,
      "length_km": 155,
      "status": "operational",
      "is_hvdc": false,
      "owner": "AEP Texas",
      "data_source": "HIFLD"
    },
    {
      "id": "branch-harlingen-brownsville",
      "name": "Harlingen - Brownsville",
      "from_node_id": "node-south-texas-harlingen",
      "to_node_id": "node-south-texas-brownsville",
      "voltage_kv": 138,
      "capacity_mw": 400,
      "length_km": 35,
      "status": "operational",
      "is_hvdc": false,
      "owner": "AEP Texas",
      "data_source": "HIFLD"
    },
    {
      "id": "branch-harlingen-mcallen",
      "name": "Harlingen - McAllen",
      "from_node_id": "node-south-texas-harlingen",
      "to_node_id": "node-south-texas-mcallen",
      "voltage_kv": 138,
      "capacity_mw": 400,
      "length_km": 52,
      "status": "operational",
      "is_hvdc": false,
      "owner": "AEP Texas",
      "data_source": "HIFLD"
    },
    {
      "id": "branch-mcallen-rio-nogales",
      "name": "McAllen - Rio Nogales",
      "from_node_id": "node-south-texas-mcallen",
      "to_node_id": "node-rio-nogales",
      "voltage_kv": 345,
      "capacity_mw": 1000,
      "length_km": 28,
      "status": "operational",
      "is_hvdc": false,
      "owner": "AEP Texas",
      "data_source": "HIFLD"
    },
    {
      "id": "branch-rio-nogales-laredo",
      "name": "Rio Nogales - Laredo",
      "from_node_id": "node-rio-nogales",
      "to_node_id": "node-south-texas-laredo",
      "voltage_kv": 138,
      "capacity_mw": 400,
      "length_km": 125,
      "status": "operational",
      "is_hvdc": false,
      "owner": "AEP Texas",
      "data_source": "HIFLD"
    },
    {
      "id": "branch-laredo-cotulla",
      "name": "Laredo - Cotulla",
      "from_node_id": "node-south-texas-laredo",
      "to_node_id": "node-cotulla",
      "voltage_kv": 345,
      "capacity_mw": 1000,
      "length_km": 85,
      "status": "operational",
      "is_hvdc": false,
      "owner": "AEP Texas",
      "data_source": "HIFLD"
    },
    {
      "id": "branch-cotulla-pearsall",
      "name": "Cotulla - Pearsall",
      "from_node_id": "node-cotulla",
      "to_node_id": "node-pearsall",
      "voltage_kv": 345,
      "capacity_mw": 1000,
      "length_km": 55,
      "status": "operational",
      "is_hvdc": false,
      "owner": "AEP Texas",
      "data_source": "HIFLD"
    },
    {
      "id": "branch-pearsall-uvalde",
      "name": "Pearsall - Uvalde",
      "from_node_id": "node-pearsall",
      "to_node_id": "node-uvalde",
      "voltage_kv": 345,
      "capacity_mw": 1000,
      "length_km": 72,
      "status": "operational",
      "is_hvdc": false,
      "owner": "AEP Texas",
      "data_source": "HIFLD"
    },
    {
      "id": "branch-pearsall-cagnon",
      "name": "Pearsall - Cagnon",
      "from_node_id": "node-pearsall",
      "to_node_id": "node-san-antonio-cagnon",
      "voltage_kv": 345,
      "capacity_mw": 1200,
      "length_km": 62,
      "status": "operational",
      "is_hvdc": false,
      "owner": "CPS Energy / AEP",
      "data_source": "HIFLD"
    },
    {
      "id": "branch-comanche-peak-zenith",
      "name": "Comanche Peak - Zenith",
      "from_node_id": "node-nuclear-comanche-peak",
      "to_node_id": "node-zenith",
      "voltage_kv": 345,
      "capacity_mw": 1500,
      "length_km": 52,
      "status": "operational",
      "is_hvdc": false,
      "owner": "Oncor Electric",
      "data_source": "HIFLD"
    },
    {
      "id": "branch-zenith-waco",
      "name": "Zenith - Waco",
      "from_node_id": "node-zenith",
      "to_node_id": "node-waco",
      "voltage_kv": 345,
      "capacity_mw": 1200,
      "length_km": 75,
      "status": "operational",
      "is_hvdc": false,
      "owner": "Oncor Electric",
      "data_source": "HIFLD"
    },
    {
      "id": "branch-waco-temple",
      "name": "Waco - Temple",
      "from_node_id": "node-waco",
      "to_node_id": "node-temple",
      "voltage_kv": 345,
      "capacity_mw": 1200,
      "length_km": 55,
      "status": "operational",
      "is_hvdc": false,
      "owner": "Oncor Electric",
      "data_source": "HIFLD"
    },
    {
      "id": "branch-temple-killeen",
      "name": "Temple - Killeen",
      "from_node_id": "node-temple",
      "to_node_id": "node-killeen",
      "voltage_kv": 345,
      "capacity_mw": 1000,
      "length_km": 38,
      "status": "operational",
      "is_hvdc": false,
      "owner": "Oncor Electric",
      "data_source": "HIFLD"
    },
    {
      "id": "branch-killeen-austin-south",
      "name": "Killeen - Austin South",
      "from_node_id": "node-killeen",
      "to_node_id": "node-austin-south",
      "voltage_kv": 345,
      "capacity_mw": 1000,
      "length_km": 95,
      "status": "operational",
      "is_hvdc": false,
      "owner": "Austin Energy",
      "data_source": "HIFLD"
    },
    {
      "id": "branch-navarro-big-brown",
      "name": "Navarro - Big Brown",
      "from_node_id": "node-navarro",
      "to_node_id": "node-big-brown",
      "voltage_kv": 345,
      "capacity_mw": 1500,
      "length_km": 45,
      "status": "operational",
      "is_hvdc": false,
      "owner": "Oncor Electric",
      "data_source": "HIFLD"
    },
    {
      "id": "branch-big-brown-limestone",
      "name": "Big Brown - Limestone",
      "from_node_id": "node-big-brown",
      "to_node_id": "node-limestone",
      "voltage_kv": 345,
      "capacity_mw": 1500,
      "length_km": 48,
      "status": "operational",
      "is_hvdc": false,
      "owner": "Oncor Electric",
      "data_source": "HIFLD"
    },
    {
      "id": "branch-limestone-jewett",
      "name": "Limestone - Jewett",
      "from_node_id": "node-limestone",
      "to_node_id": "node-jewett",
      "voltage_kv": 345,
      "capacity_mw": 1200,
      "length_km": 12,
      "status": "operational",
      "is_hvdc": false,
      "owner": "Oncor Electric",
      "data_source": "HIFLD"
    },
    {
      "id": "branch-jewett-twin-oaks",
      "name": "Jewett - Twin Oaks",
      "from_node_id": "node-jewett",
      "to_node_id": "node-twin-oaks",
      "voltage_kv": 345,
      "capacity_mw": 1000,
      "length_km": 42,
      "status": "operational",
      "is_hvdc": false,
      "owner": "Oncor Electric",
      "data_source": "HIFLD"
    },
    {
      "id": "branch-twin-oaks-gibbons-creek",
      "name": "Twin Oaks - Gibbons Creek",
      "from_node_id": "node-twin-oaks",
      "to_node_id": "node-gibbons-creek",
      "voltage_kv": 345,
      "capacity_mw": 1000,
      "length_km": 72,
      "status": "operational",
      "is_hvdc": false,
      "owner": "TMPA / Oncor",
      "data_source": "HIFLD"
    },
    {
      "id": "branch-gibbons-creek-singleton",
      "name": "Gibbons Creek - Singleton",
      "from_node_id": "node-gibbons-creek",
      "to_node_id": "node-singleton",
      "voltage_kv": 345,
      "capacity_mw": 1000,
      "length_km": 65,
      "status": "operational",
      "is_hvdc": false,
      "owner": "CenterPoint Energy",
      "data_source": "HIFLD"
    },
    {
      "id": "branch-limestone-oak-grove",
      "name": "Limestone - Oak Grove",
      "from_node_id": "node-limestone",
      "to_node_id": "node-oak-grove",
      "voltage_kv": 345,
      "capacity_mw": 1500,
      "length_km": 38,
      "status": "operational",
      "is_hvdc": false,
      "owner": "Oncor Electric",
      "data_source": "HIFLD"
    },
    {
      "id": "branch-comanche-peak-wolf-hollow",
      "name": "Comanche Peak - Wolf Hollow",
      "from_node_id": "node-nuclear-comanche-peak",
      "to_node_id": "node-wolf-hollow",
      "voltage_kv": 345,
      "capacity_mw": 1200,
      "length_km": 22,
      "status": "operational",
      "is_hvdc": false,
      "owner": "Oncor Electric",
      "data_source": "HIFLD"
    },
    {
      "id": "branch-wolf-hollow-decordova",
      "name": "Wolf Hollow - DeCordova",
      "from_node_id": "node-wolf-hollow",
      "to_node_id": "node-decordova",
      "voltage_kv": 345,
      "capacity_mw": 1200,
      "length_km": 25,
      "status": "operational",
      "is_hvdc": false,
      "owner": "Oncor Electric",
      "data_source": "HIFLD"
    },
    {
      "id": "branch-sweetwater-comanche-peak",
      "name": "Sweetwater - Comanche Peak (CREZ)",
      "from_node_id": "node-west-texas-sweetwater-sub",
      "to_node_id": "node-nuclear-comanche-peak",
      "voltage_kv": 345,
      "capacity_mw": 2400,
      "length_km": 285,
      "status": "operational",
      "is_hvdc": false,
      "owner": "Oncor Electric",
      "data_source": "ERCOT CREZ"
    },
    {
      "id": "branch-sweetwater-zenith",
      "name": "Sweetwater - Zenith (CREZ)",
      "from_node_id": "node-west-texas-sweetwater-sub",
      "to_node_id": "node-zenith",
      "voltage_kv": 345,
      "capacity_mw": 2400,
      "length_km": 245,
      "status": "operational",
      "is_hvdc": false,
      "owner": "Oncor Electric",
      "data_source": "ERCOT CREZ"
    },
    {
      "id": "branch-midland-singleton",
      "name": "Midland - Singleton (CREZ)",
      "from_node_id": "node-west-texas-midland",
      "to_node_id": "node-singleton",
      "voltage_kv": 345,
      "capacity_mw": 2400,
      "length_km": 520,
      "status": "operational",
      "is_hvdc": false,
      "owner": "Oncor Electric",
      "data_source": "ERCOT CREZ"
    },
    {
      "id": "branch-panhandle-1-panhandle-2",
      "name": "Panhandle Wind 1 - Panhandle Wind 2",
      "from_node_id": "node-wind-panhandle-1",
      "to_node_id": "node-wind-panhandle-2",
      "voltage_kv": 345,
      "capacity_mw": 1200,
      "length_km": 15,
      "status": "operational",
      "is_hvdc": false,
      "owner": "Pattern Energy",
      "data_source": "ERCOT CREZ"
    },
    {
      "id": "branch-panhandle-2-spinning-spur-1",
      "name": "Panhandle Wind 2 - Spinning Spur 1",
      "from_node_id": "node-wind-panhandle-2",
      "to_node_id": "node-wind-spinning-spur-1",
      "voltage_kv": 345,
      "capacity_mw": 1200,
      "length_km": 95,
      "status": "operational",
      "is_hvdc": false,
      "owner": "Xcel Energy",
      "data_source": "ERCOT CREZ"
    },
    {
      "id": "branch-spinning-spur-1-2",
      "name": "Spinning Spur 1 - Spinning Spur 2",
      "from_node_id": "node-wind-spinning-spur-1",
      "to_node_id": "node-wind-spinning-spur-2",
      "voltage_kv": 345,
      "capacity_mw": 800,
      "length_km": 5,
      "status": "operational",
      "is_hvdc": false,
      "owner": "EDF Renewables",
      "data_source": "ERCOT CREZ"
    },
    {
      "id": "branch-spinning-spur-2-3",
      "name": "Spinning Spur 2 - Spinning Spur 3",
      "from_node_id": "node-wind-spinning-spur-2",
      "to_node_id": "node-wind-spinning-spur-3",
      "voltage_kv": 345,
      "capacity_mw": 800,
      "length_km": 5,
      "status": "operational",
      "is_hvdc": false,
      "owner": "EDF Renewables",
      "data_source": "ERCOT CREZ"
    },
    {
      "id": "branch-big-spring-capricorn-ridge",
      "name": "Big Spring - Capricorn Ridge",
      "from_node_id": "node-west-texas-big-spring",
      "to_node_id": "node-wind-capricorn-ridge",
      "voltage_kv": 345,
      "capacity_mw": 1500,
      "length_km": 62,
      "status": "operational",
      "is_hvdc": false,
      "owner": "Oncor Electric",
      "data_source": "ERCOT CREZ"
    },
    {
      "id": "branch-sweetwater-sub-sweetwater-wind",
      "name": "Sweetwater Sub - Sweetwater Wind",
      "from_node_id": "node-west-texas-sweetwater-sub",
      "to_node_id": "node-wind-sweetwater",
      "voltage_kv": 345,
      "capacity_mw": 1200,
      "length_km": 8,
      "status": "operational",
      "is_hvdc": false,
      "owner": "Oncor Electric",
      "data_source": "HIFLD"
    },
    {
      "id": "branch-jones-county-buffalo-gap",
      "name": "Jones County - Buffalo Gap",
      "from_node_id": "node-west-texas-jones-county",
      "to_node_id": "node-wind-buffalo-gap",
      "voltage_kv": 345,
      "capacity_mw": 1200,
      "length_km": 45,
      "status": "operational",
      "is_hvdc": false,
      "owner": "Oncor Electric",
      "data_source": "HIFLD"
    },
    {
      "id": "branch-permian-roadrunner",
      "name": "Permian Basin - Roadrunner Solar",
      "from_node_id": "node-permian-basin",
      "to_node_id": "node-solar-roadrunner",
      "voltage_kv": 345,
      "capacity_mw": 1000,
      "length_km": 22,
      "status": "operational",
      "is_hvdc": false,
      "owner": "Oncor Electric",
      "data_source": "HIFLD"
    },
    {
      "id": "branch-permian-phoebe",
      "name": "Permian Basin - Phoebe Solar",
      "from_node_id": "node-permian-basin",
      "to_node_id": "node-solar-phoebe",
      "voltage_kv": 345,
      "capacity_mw": 800,
      "length_km": 18,
      "status": "operational",
      "is_hvdc": false,
      "owner": "Oncor Electric",
      "data_source": "HIFLD"
    },
    {
      "id": "branch-odessa-oberon",
      "name": "Odessa - Oberon Solar",
      "from_node_id": "node-west-texas-odessa",
      "to_node_id": "node-solar-oberon",
      "voltage_kv": 345,
      "capacity_mw": 800,
      "length_km": 48,
      "status": "operational",
      "is_hvdc": false,
      "owner": "Oncor Electric",
      "data_source": "HIFLD"
    },
    {
      "id": "branch-permian-misae",
      "name": "Permian Basin - Misae Solar",
      "from_node_id": "node-permian-basin",
      "to_node_id": "node-solar-misae",
      "voltage_kv": 345,
      "capacity_mw": 600,
      "length_km": 15,
      "status": "operational",
      "is_hvdc": false,
      "owner": "Oncor Electric",
      "data_source": "HIFLD"
    },
    {
      "id": "branch-permian-lapetus",
      "name": "Permian Basin - Lapetus Solar",
      "from_node_id": "node-permian-basin",
      "to_node_id": "node-solar-lapetus",
      "voltage_kv": 345,
      "capacity_mw": 600,
      "length_km": 12,
      "status": "operational",
      "is_hvdc": false,
      "owner": "Oncor Electric",
      "data_source": "HIFLD"
    },
    {
      "id": "branch-permian-aktina",
      "name": "Permian Basin - Aktina Solar",
      "from_node_id": "node-permian-basin",
      "to_node_id": "node-solar-aktina",
      "voltage_kv": 345,
      "capacity_mw": 800,
      "length_km": 20,
      "status": "operational",
      "is_hvdc": false,
      "owner": "Oncor Electric",
      "data_source": "HIFLD"
    },
    {
      "id": "branch-permian-fighting-jays",
      "name": "Permian Basin - Fighting Jays Solar",
      "from_node_id": "node-permian-basin",
      "to_node_id": "node-solar-fighting-jays",
      "voltage_kv": 345,
      "capacity_mw": 800,
      "length_km": 75,
      "status": "operational",
      "is_hvdc": false,
      "owner": "Oncor Electric",
      "data_source": "HIFLD"
    },
    {
      "id": "branch-odessa-ector-odessa-sub",
      "name": "Odessa-Ector - Odessa Substation",
      "from_node_id": "node-gas-odessa-ector",
      "to_node_id": "node-west-texas-odessa",
      "voltage_kv": 345,
      "capacity_mw": 1200,
      "length_km": 5,
      "status": "operational",
      "is_hvdc": false,
      "owner": "Oncor Electric",
      "data_source": "HIFLD"
    },
    {
      "id": "branch-permian-peaking-permian",
      "name": "Permian Basin Peaking - Permian Basin",
      "from_node_id": "node-gas-permian-basin-1",
      "to_node_id": "node-permian-basin",
      "voltage_kv": 345,
      "capacity_mw": 800,
      "length_km": 12,
      "status": "operational",
      "is_hvdc": false,
      "owner": "Oncor Electric",
      "data_source": "HIFLD"
    },
    {
      "id": "branch-dfw-houston-1",
      "name": "DFW - Houston Backbone North (Forney-Trinidad)",
      "from_node_id": "node-dfw-forney",
      "to_node_id": "node-trinidad",
      "voltage_kv": 345,
      "capacity_mw": 1800,
      "length_km": 95,
      "status": "operational",
      "is_hvdc": false,
      "owner": "Oncor Electric",
      "data_source": "ERCOT Planning"
    },
    {
      "id": "branch-trinidad-navarro",
      "name": "Trinidad - Navarro",
      "from_node_id": "node-trinidad",
      "to_node_id": "node-navarro",
      "voltage_kv": 345,
      "capacity_mw": 1500,
      "length_km": 35,
      "status": "operational",
      "is_hvdc": false,
      "owner": "Oncor Electric",
      "data_source": "ERCOT Planning"
    },
    {
      "id": "branch-trinidad-big-brown",
      "name": "Trinidad - Big Brown",
      "from_node_id": "node-trinidad",
      "to_node_id": "node-big-brown",
      "voltage_kv": 345,
      "capacity_mw": 1500,
      "length_km": 42,
      "status": "operational",
      "is_hvdc": false,
      "owner": "Oncor Electric",
      "data_source": "ERCOT Planning"
    },
    {
      "id": "branch-limestone-sub-limestone",
      "name": "Limestone Switching - Limestone Plant",
      "from_node_id": "node-limestone-sub",
      "to_node_id": "node-limestone",
      "voltage_kv": 345,
      "capacity_mw": 1800,
      "length_km": 3,
      "status": "operational",
      "is_hvdc": false,
      "owner": "Oncor Electric",
      "data_source": "HIFLD"
    },
    {
      "id": "branch-houston-san-antonio-1",
      "name": "Houston - San Antonio Backbone (Singleton-Fayette)",
      "from_node_id": "node-singleton",
      "to_node_id": "node-austin-fayette",
      "voltage_kv": 345,
      "capacity_mw": 1500,
      "length_km": 95,
      "status": "operational",
      "is_hvdc": false,
      "owner": "LCRA",
      "data_source": "ERCOT Planning"
    },
    {
      "id": "branch-fayette-austin-south",
      "name": "Fayette - Austin South",
      "from_node_id": "node-austin-fayette",
      "to_node_id": "node-austin-south",
      "voltage_kv": 345,
      "capacity_mw": 1500,
      "length_km": 85,
      "status": "operational",
      "is_hvdc": false,
      "owner": "LCRA / Austin Energy",
      "data_source": "ERCOT Planning"
    },
    {
      "id": "branch-seguin-calaveras",
      "name": "Seguin - Calaveras",
      "from_node_id": "node-seguin",
      "to_node_id": "node-san-antonio-calaveras",
      "voltage_kv": 345,
      "capacity_mw": 1200,
      "length_km": 65,
      "status": "operational",
      "is_hvdc": false,
      "owner": "CPS Energy",
      "data_source": "ERCOT Planning"
    },
    {
      "id": "branch-dfw-san-antonio-1",
      "name": "DFW - San Antonio Backbone (Grandview-Waco)",
      "from_node_id": "node-grandview",
      "to_node_id": "node-waco",
      "voltage_kv": 345,
      "capacity_mw": 1500,
      "length_km": 85,
      "status": "operational",
      "is_hvdc": false,
      "owner": "Oncor Electric",
      "data_source": "ERCOT Planning"
    },
    {
      "id": "branch-temple-fayette",
      "name": "Temple - Fayette",
      "from_node_id": "node-temple",
      "to_node_id": "node-austin-fayette",
      "voltage_kv": 345,
      "capacity_mw": 1200,
      "length_km": 120,
      "status": "operational",
      "is_hvdc": false,
      "owner": "LCRA / Oncor",
      "data_source": "ERCOT Planning"
    },
    {
      "id": "branch-texas-city-galveston",
      "name": "Texas City - Galveston",
      "from_node_id": "node-coastal-texas-city",
      "to_node_id": "node-coastal-galveston",
      "voltage_kv": 138,
      "capacity_mw": 400,
      "length_km": 18,
      "status": "operational",
      "is_hvdc": false,
      "owner": "CenterPoint Energy",
      "data_source": "HIFLD"
    },
    {
      "id": "branch-houston-nw-greens-bayou",
      "name": "Houston Northwest - Greens Bayou",
      "from_node_id": "node-houston-northwest",
      "to_node_id": "node-houston-greens-bayou",
      "voltage_kv": 345,
      "capacity_mw": 1200,
      "length_km": 22,
      "status": "operational",
      "is_hvdc": false,
      "owner": "CenterPoint Energy",
      "data_source": "HIFLD"
    },
    {
      "id": "branch-deer-park-baytown",
      "name": "Deer Park - Baytown",
      "from_node_id": "node-houston-deer-park",
      "to_node_id": "node-coastal-baytown",
      "voltage_kv": 345,
      "capacity_mw": 1200,
      "length_km": 18,
      "status": "operational",
      "is_hvdc": false,
      "owner": "CenterPoint Energy",
      "data_source": "HIFLD"
    },
    {
      "id": "branch-deer-park-polk",
      "name": "Deer Park - Polk",
      "from_node_id": "node-houston-deer-park",
      "to_node_id": "node-houston-polk",
      "voltage_kv": 345,
      "capacity_mw": 1200,
      "length_km": 28,
      "status": "operational",
      "is_hvdc": false,
      "owner": "CenterPoint Energy",
      "data_source": "HIFLD"
    },
    {
      "id": "branch-gulf-wind-valley",
      "name": "Gulf Wind - Valley Switching",
      "from_node_id": "node-wind-gulf-wind",
      "to_node_id": "node-south-texas-valley",
      "voltage_kv": 345,
      "capacity_mw": 800,
      "length_km": 65,
      "status": "operational",
      "is_hvdc": false,
      "owner": "AEP Texas",
      "data_source": "ERCOT CREZ"
    },
    {
      "id": "branch-valley-rgv-1",
      "name": "Valley Switching - RGV 1",
      "from_node_id": "node-south-texas-valley",
      "to_node_id": "node-south-texas-rgv-1",
      "voltage_kv": 345,
      "capacity_mw": 1000,
      "length_km": 25,
      "status": "operational",
      "is_hvdc": false,
      "owner": "AEP Texas",
      "data_source": "HIFLD"
    },
    {
      "id": "branch-rgv-1-mcallen",
      "name": "RGV 1 - McAllen",
      "from_node_id": "node-south-texas-rgv-1",
      "to_node_id": "node-south-texas-mcallen",
      "voltage_kv": 138,
      "capacity_mw": 400,
      "length_km": 15,
      "status": "operational",
      "is_hvdc": false,
      "owner": "AEP Texas",
      "data_source": "HIFLD"
    },
    {
      "id": "branch-valley-harlingen",
      "name": "Valley Switching - Harlingen",
      "from_node_id": "node-south-texas-valley",
      "to_node_id": "node-south-texas-harlingen",
      "voltage_kv": 138,
      "capacity_mw": 400,
      "length_km": 22,
      "status": "operational",
      "is_hvdc": false,
      "owner": "AEP Texas",
      "data_source": "HIFLD"
    },
    {
      "id": "branch-corpus-valley",
      "name": "Corpus Christi - Valley Switching",
      "from_node_id": "node-south-texas-corpus-christi",
      "to_node_id": "node-south-texas-valley",
      "voltage_kv": 345,
      "capacity_mw": 1200,
      "length_km": 165,
      "status": "operational",
      "is_hvdc": false,
      "owner": "AEP Texas",
      "data_source": "HIFLD"
    },
    {
      "id": "branch-big-spring-lubbock",
      "name": "Big Spring - Lubbock (CREZ)",
      "from_node_id": "node-west-texas-big-spring",
      "to_node_id": "node-west-texas-lubbock",
      "voltage_kv": 345,
      "capacity_mw": 2000,
      "length_km": 150,
      "status": "operational",
      "is_hvdc": false,
      "owner": "Oncor Electric",
      "data_source": "ERCOT CREZ"
    },
    {
      "id": "branch-midland-crez-wa-parish",
      "name": "Midland - W.A. Parish (CREZ South)",
      "from_node_id": "node-west-texas-midland",
      "to_node_id": "node-houston-w-a-parish",
      "voltage_kv": 345,
      "capacity_mw": 2400,
      "length_km": 485,
      "status": "operational",
      "is_hvdc": false,
      "owner": "Oncor Electric / CenterPoint",
      "data_source": "ERCOT CREZ"
    },
    {
      "id": "branch-permian-san-antonio",
      "name": "Permian Basin - San Antonio (CREZ Southwest)",
      "from_node_id": "node-permian-basin",
      "to_node_id": "node-san-antonio-tesoro",
      "voltage_kv": 345,
      "capacity_mw": 2000,
      "length_km": 380,
      "status": "operational",
      "is_hvdc": false,
      "owner": "Oncor Electric / CPS Energy",
      "data_source": "ERCOT CREZ"
    },
    {
      "id": "branch-north-texas-parkdale",
      "name": "North Texas - Parkdale",
      "from_node_id": "node-dfw-north-texas",
      "to_node_id": "node-dfw-parkdale",
      "voltage_kv": 345,
      "capacity_mw": 1200,
      "length_km": 35,
      "status": "operational",
      "is_hvdc": false,
      "owner": "Oncor Electric",
      "data_source": "HIFLD"
    },
    {
      "id": "branch-eagle-mountain-comanche-peak",
      "name": "Eagle Mountain - Comanche Peak",
      "from_node_id": "node-dfw-eagle-mountain",
      "to_node_id": "node-nuclear-comanche-peak",
      "voltage_kv": 345,
      "capacity_mw": 1500,
      "length_km": 72,
      "status": "operational",
      "is_hvdc": false,
      "owner": "Oncor Electric",
      "data_source": "HIFLD"
    },
    {
      "id": "branch-decordova-trinity",
      "name": "DeCordova - Trinity",
      "from_node_id": "node-decordova",
      "to_node_id": "node-dfw-trinity",
      "voltage_kv": 345,
      "capacity_mw": 1200,
      "length_km": 42,
      "status": "operational",
      "is_hvdc": false,
      "owner": "Oncor Electric",
      "data_source": "HIFLD"
    },
    {
      "id": "branch-lamar-panda-sherman",
      "name": "Lamar - Panda Sherman",
      "from_node_id": "node-dfw-lamar",
      "to_node_id": "node-panda-sherman",
      "voltage_kv": 345,
      "capacity_mw": 1000,
      "length_km": 95,
      "status": "operational",
      "is_hvdc": false,
      "owner": "Oncor Electric",
      "data_source": "HIFLD"
    },
    {
      "id": "branch-lamar-monticello",
      "name": "Lamar - Monticello",
      "from_node_id": "node-dfw-lamar",
      "to_node_id": "node-monticello",
      "voltage_kv": 345,
      "capacity_mw": 1200,
      "length_km": 72,
      "status": "operational",
      "is_hvdc": false,
      "owner": "Oncor Electric",
      "data_source": "HIFLD"
    },
    {
      "id": "branch-uvalde-del-rio",
      "name": "Uvalde - Del Rio",
      "from_node_id": "node-uvalde",
      "to_node_id": "node-del-rio",
      "voltage_kv": 138,
      "capacity_mw": 300,
      "length_km": 115,
      "status": "operational",
      "is_hvdc": false,
      "owner": "AEP Texas",
      "data_source": "HIFLD"
    },
    {
      "id": "branch-uvalde-eagle-pass",
      "name": "Uvalde - Eagle Pass",
      "from_node_id": "node-uvalde",
      "to_node_id": "node-eagle-pass",
      "voltage_kv": 138,
      "capacity_mw": 300,
      "length_km": 85,
      "status": "operational",
      "is_hvdc": false,
      "owner": "AEP Texas",
      "data_source": "HIFLD"
    },
    {
      "id": "branch-singleton-houston-nw",
      "name": "Singleton - Houston Northwest",
      "from_node_id": "node-singleton",
      "to_node_id": "node-houston-northwest",
      "voltage_kv": 345,
      "capacity_mw": 1200,
      "length_km": 55,
      "status": "operational",
      "is_hvdc": false,
      "owner": "CenterPoint Energy",
      "data_source": "HIFLD"
    },
    {
      "id": "branch-victoria-stp",
      "name": "Victoria - South Texas Project (Loop)",
      "from_node_id": "node-south-texas-victoria",
      "to_node_id": "node-nuclear-south-texas-project",
      "voltage_kv": 345,
      "capacity_mw": 1800,
      "length_km": 85,
      "status": "operational",
      "is_hvdc": false,
      "owner": "AEP Texas / STPNOC",
      "data_source": "HIFLD"
    },
    {
      "id": "branch-san-patricio-stp",
      "name": "San Patricio - South Texas Project",
      "from_node_id": "node-coastal-san-patricio",
      "to_node_id": "node-nuclear-south-texas-project",
      "voltage_kv": 345,
      "capacity_mw": 1500,
      "length_km": 95,
      "status": "operational",
      "is_hvdc": false,
      "owner": "AEP Texas",
      "data_source": "HIFLD"
    },
    {
      "id": "branch-freeport-texas-city",
      "name": "Freeport - Texas City",
      "from_node_id": "node-coastal-freeport",
      "to_node_id": "node-coastal-texas-city",
      "voltage_kv": 345,
      "capacity_mw": 1000,
      "length_km": 55,
      "status": "operational",
      "is_hvdc": false,
      "owner": "CenterPoint Energy",
      "data_source": "HIFLD"
    },
    {
      "id": "branch-oak-grove-singleton",
      "name": "Oak Grove - Singleton",
      "from_node_id": "node-oak-grove",
      "to_node_id": "node-singleton",
      "voltage_kv": 345,
      "capacity_mw": 1500,
      "length_km": 125,
      "status": "operational",
      "is_hvdc": false,
      "owner": "Oncor Electric / CenterPoint",
      "data_source": "HIFLD"
    },
    {
      "id": "branch-jewett-gibbons-creek",
      "name": "Jewett - Gibbons Creek",
      "from_node_id": "node-jewett",
      "to_node_id": "node-gibbons-creek",
      "voltage_kv": 345,
      "capacity_mw": 1000,
      "length_km": 85,
      "status": "operational",
      "is_hvdc": false,
      "owner": "Oncor Electric",
      "data_source": "HIFLD"
    },
    {
      "id": "branch-lost-pines-gibbons-creek",
      "name": "Lost Pines - Gibbons Creek",
      "from_node_id": "node-lost-pines",
      "to_node_id": "node-gibbons-creek",
      "voltage_kv": 345,
      "capacity_mw": 1000,
      "length_km": 52,
      "status": "operational",
      "is_hvdc": false,
      "owner": "LCRA",
      "data_source": "HIFLD"
    },
    {
      "id": "branch-sand-hill-mcneil",
      "name": "Sand Hill - McNeil",
      "from_node_id": "node-austin-sand-hill",
      "to_node_id": "node-austin-mcneil",
      "voltage_kv": 138,
      "capacity_mw": 500,
      "length_km": 8,
      "status": "operational",
      "is_hvdc": false,
      "owner": "Austin Energy",
      "data_source": "HIFLD"
    },
    {
      "id": "branch-panhandle-1-lubbock-2",
      "name": "Panhandle Wind 1 - Lubbock (Direct CREZ)",
      "from_node_id": "node-wind-panhandle-1",
      "to_node_id": "node-west-texas-lubbock",
      "voltage_kv": 345,
      "capacity_mw": 2000,
      "length_km": 185,
      "status": "operational",
      "is_hvdc": false,
      "owner": "Xcel Energy",
      "data_source": "ERCOT CREZ"
    },
    {
      "id": "branch-roscoe-sweetwater-wind",
      "name": "Roscoe - Sweetwater Wind",
      "from_node_id": "node-wind-roscoe",
      "to_node_id": "node-wind-sweetwater",
      "voltage_kv": 345,
      "capacity_mw": 1200,
      "length_km": 12,
      "status": "operational",
      "is_hvdc": false,
      "owner": "Oncor Electric",
      "data_source": "HIFLD"
    },
    {
      "id": "branch-horse-hollow-buffalo-gap",
      "name": "Horse Hollow - Buffalo Gap",
      "from_node_id": "node-wind-horse-hollow",
      "to_node_id": "node-wind-buffalo-gap",
      "voltage_kv": 345,
      "capacity_mw": 1200,
      "length_km": 45,
      "status": "operational",
      "is_hvdc": false,
      "owner": "Oncor Electric",
      "data_source": "HIFLD"
    },
    {
      "id": "branch-capricorn-notrees",
      "name": "Capricorn Ridge - Notrees",
      "from_node_id": "node-wind-capricorn-ridge",
      "to_node_id": "node-wind-notrees",
      "voltage_kv": 345,
      "capacity_mw": 1000,
      "length_km": 95,
      "status": "operational",
      "is_hvdc": false,
      "owner": "Oncor Electric",
      "data_source": "HIFLD"
    },
    {
      "id": "branch-notrees-king-mountain",
      "name": "Notrees - King Mountain",
      "from_node_id": "node-wind-notrees",
      "to_node_id": "node-wind-king-mountain",
      "voltage_kv": 345,
      "capacity_mw": 800,
      "length_km": 95,
      "status": "operational",
      "is_hvdc": false,
      "owner": "Oncor Electric",
      "data_source": "HIFLD"
    },
    {
      "id": "branch-roadrunner-fighting-jays",
      "name": "Roadrunner - Fighting Jays Solar",
      "from_node_id": "node-solar-roadrunner",
      "to_node_id": "node-solar-fighting-jays",
      "voltage_kv": 345,
      "capacity_mw": 600,
      "length_km": 62,
      "status": "operational",
      "is_hvdc": false,
      "owner": "Oncor Electric",
      "data_source": "HIFLD"
    },
    {
      "id": "branch-oberon-notrees",
      "name": "Oberon Solar - Notrees",
      "from_node_id": "node-solar-oberon",
      "to_node_id": "node-wind-notrees",
      "voltage_kv": 345,
      "capacity_mw": 600,
      "length_km": 32,
      "status": "operational",
      "is_hvdc": false,
      "owner": "Oncor Electric",
      "data_source": "HIFLD"
    },
    {
      "id": "branch-midlothian-navarro",
      "name": "Midlothian - Navarro",
      "from_node_id": "node-dfw-midlothian",
      "to_node_id": "node-navarro",
      "voltage_kv": 345,
      "capacity_mw": 1200,
      "length_km": 55,
      "status": "operational",
      "is_hvdc": false,
      "owner": "Oncor Electric",
      "data_source": "HIFLD"
    },
    {
      "id": "branch-anna-lamar",
      "name": "Anna - Lamar",
      "from_node_id": "node-dfw-anna",
      "to_node_id": "node-dfw-lamar",
      "voltage_kv": 345,
      "capacity_mw": 1000,
      "length_km": 115,
      "status": "operational",
      "is_hvdc": false,
      "owner": "Oncor Electric",
      "data_source": "HIFLD"
    },
    {
      "id": "branch-sugarland-freeport",
      "name": "Sugar Land - Freeport",
      "from_node_id": "node-houston-sugarland",
      "to_node_id": "node-coastal-freeport",
      "voltage_kv": 345,
      "capacity_mw": 1000,
      "length_km": 72,
      "status": "operational",
      "is_hvdc": false,
      "owner": "CenterPoint Energy",
      "data_source": "HIFLD"
    },
    {
      "id": "branch-katy-singleton",
      "name": "Katy - Singleton",
      "from_node_id": "node-houston-katy",
      "to_node_id": "node-singleton",
      "voltage_kv": 345,
      "capacity_mw": 1200,
      "length_km": 42,
      "status": "operational",
      "is_hvdc": false,
      "owner": "CenterPoint Energy",
      "data_source": "HIFLD"
    },
    {
      "id": "branch-cagnon-uvalde",
      "name": "Cagnon - Uvalde",
      "from_node_id": "node-san-antonio-cagnon",
      "to_node_id": "node-uvalde",
      "voltage_kv": 345,
      "capacity_mw": 1000,
      "length_km": 95,
      "status": "operational",
      "is_hvdc": false,
      "owner": "CPS Energy / AEP",
      "data_source": "HIFLD"
    },
    {
      "id": "branch-seguin-victoria",
      "name": "Seguin - Victoria",
      "from_node_id": "node-seguin",
      "to_node_id": "node-south-texas-victoria",
      "voltage_kv": 345,
      "capacity_mw": 1200,
      "length_km": 135,
      "status": "operational",
      "is_hvdc": false,
      "owner": "CPS Energy / AEP",
      "data_source": "HIFLD"
    },
    {
      "id": "branch-coleto-freeport",
      "name": "Coleto Creek - Freeport",
      "from_node_id": "node-coastal-coleto-creek",
      "to_node_id": "node-coastal-freeport",
      "voltage_kv": 345,
      "capacity_mw": 1200,
      "length_km": 185,
      "status": "operational",
      "is_hvdc": false,
      "owner": "AEP Texas / CenterPoint",
      "data_source": "HIFLD"
    },
    {
      "id": "branch-nueces-gulf-wind",
      "name": "Nueces Bay - Gulf Wind",
      "from_node_id": "node-coastal-nueces-bay",
      "to_node_id": "node-wind-gulf-wind",
      "voltage_kv": 345,
      "capacity_mw": 600,
      "length_km": 95,
      "status": "operational",
      "is_hvdc": false,
      "owner": "AEP Texas",
      "data_source": "HIFLD"
    },
    {
      "id": "branch-barney-davis-gulf-wind",
      "name": "Barney Davis - Gulf Wind",
      "from_node_id": "node-barney-davis",
      "to_node_id": "node-wind-gulf-wind",
      "voltage_kv": 345,
      "capacity_mw": 600,
      "length_km": 82,
      "status": "operational",
      "is_hvdc": false,
      "owner": "AEP Texas",
      "data_source": "HIFLD"
    },
    {
      "id": "branch-rio-nogales-valley",
      "name": "Rio Nogales - Valley Switching",
      "from_node_id": "node-rio-nogales",
      "to_node_id": "node-south-texas-valley",
      "voltage_kv": 345,
      "capacity_mw": 1000,
      "length_km": 55,
      "status": "operational",
      "is_hvdc": false,
      "owner": "AEP Texas",
      "data_source": "HIFLD"
    },
    {
      "id": "branch-cotulla-rio-nogales",
      "name": "Cotulla - Rio Nogales",
      "from_node_id": "node-cotulla",
      "to_node_id": "node-rio-nogales",
      "voltage_kv": 345,
      "capacity_mw": 1000,
      "length_km": 145,
      "status": "operational",
      "is_hvdc": false,
      "owner": "AEP Texas",
      "data_source": "HIFLD"
    },
    {
      "id": "branch-spinning-spur-3-lubbock",
      "name": "Spinning Spur 3 - Lubbock (Panhandle CREZ)",
      "from_node_id": "node-wind-spinning-spur-3",
      "to_node_id": "node-west-texas-lubbock",
      "voltage_kv": 345,
      "capacity_mw": 1500,
      "length_km": 220,
      "status": "operational",
      "is_hvdc": false,
      "owner": "Xcel Energy",
      "data_source": "ERCOT CREZ"
    },
    {
      "id": "branch-fluvanna-big-spring",
      "name": "Fluvanna - Big Spring",
      "from_node_id": "node-wind-fluvanna",
      "to_node_id": "node-west-texas-big-spring",
      "voltage_kv": 345,
      "capacity_mw": 1200,
      "length_km": 55,
      "status": "operational",
      "is_hvdc": false,
      "owner": "Oncor Electric",
      "data_source": "HIFLD"
    },
    {
      "id": "branch-colorado-city-capricorn",
      "name": "Colorado City - Capricorn Ridge",
      "from_node_id": "node-west-texas-colorado-city",
      "to_node_id": "node-wind-capricorn-ridge",
      "voltage_kv": 345,
      "capacity_mw": 1200,
      "length_km": 65,
      "status": "operational",
      "is_hvdc": false,
      "owner": "Oncor Electric",
      "data_source": "HIFLD"
    },
    {
      "id": "branch-forney-trinidad",
      "name": "Forney - Trinidad (Alternate)",
      "from_node_id": "node-dfw-forney",
      "to_node_id": "node-trinidad",
      "voltage_kv": 345,
      "capacity_mw": 1500,
      "length_km": 82,
      "status": "operational",
      "is_hvdc": false,
      "owner": "Oncor Electric",
      "data_source": "HIFLD"
    },
    {
      "id": "branch-zenith-grandview",
      "name": "Zenith - Grandview",
      "from_node_id": "node-zenith",
      "to_node_id": "node-grandview",
      "voltage_kv": 345,
      "capacity_mw": 1200,
      "length_km": 22,
      "status": "operational",
      "is_hvdc": false,
      "owner": "Oncor Electric",
      "data_source": "HIFLD"
    },
    {
      "id": "branch-handley-forney",
      "name": "Handley - Forney",
      "from_node_id": "node-dfw-handley",
      "to_node_id": "node-dfw-forney",
      "voltage_kv": 345,
      "capacity_mw": 1200,
      "length_km": 32,
      "status": "operational",
      "is_hvdc": false,
      "owner": "Oncor Electric",
      "data_source": "HIFLD"
    },
    {
      "id": "branch-austin-south-temple",
      "name": "Austin South - Temple",
      "from_node_id": "node-austin-south",
      "to_node_id": "node-temple",
      "voltage_kv": 345,
      "capacity_mw": 1200,
      "length_km": 102,
      "status": "operational",
      "is_hvdc": false,
      "owner": "Oncor Electric / Austin Energy",
      "data_source": "HIFLD"
    },
    {
      "id": "branch-sim-gideon-fayette",
      "name": "Sim Gideon - Fayette",
      "from_node_id": "node-sim-gideon",
      "to_node_id": "node-austin-fayette",
      "voltage_kv": 345,
      "capacity_mw": 1200,
      "length_km": 75,
      "status": "operational",
      "is_hvdc": false,
      "owner": "LCRA",
      "data_source": "HIFLD"
    },
    {
      "id": "branch-trinity-north-texas",
      "name": "Trinity - North Texas",
      "from_node_id": "node-dfw-trinity",
      "to_node_id": "node-dfw-north-texas",
      "voltage_kv": 345,
      "capacity_mw": 1200,
      "length_km": 48,
      "status": "operational",
      "is_hvdc": false,
      "owner": "Oncor Electric",
      "data_source": "HIFLD"
    },
    {
      "id": "branch-pirkey-martin-lake",
      "name": "Pirkey - Martin Lake",
      "from_node_id": "node-pirkey",
      "to_node_id": "node-dfw-martin-lake",
      "voltage_kv": 345,
      "capacity_mw": 1200,
      "length_km": 45,
      "status": "operational",
      "is_hvdc": false,
      "owner": "AEP SWEPCO",
      "data_source": "HIFLD"
    },
    {
      "id": "branch-welsh-lamar",
      "name": "Welsh - Lamar",
      "from_node_id": "node-welsh",
      "to_node_id": "node-dfw-lamar",
      "voltage_kv": 345,
      "capacity_mw": 1200,
      "length_km": 85,
      "status": "operational",
      "is_hvdc": false,
      "owner": "AEP Texas",
      "data_source": "HIFLD"
    },
    {
      "id": "branch-limestone-sub-jewett",
      "name": "Limestone Switching - Jewett",
      "from_node_id": "node-limestone-sub",
      "to_node_id": "node-jewett",
      "voltage_kv": 345,
      "capacity_mw": 1500,
      "length_km": 8,
      "status": "operational",
      "is_hvdc": false,
      "owner": "Oncor Electric",
      "data_source": "HIFLD"
    },
    {
      "id": "branch-twin-oaks-fayette",
      "name": "Twin Oaks - Fayette",
      "from_node_id": "node-twin-oaks",
      "to_node_id": "node-austin-fayette",
      "voltage_kv": 345,
      "capacity_mw": 1000,
      "length_km": 92,
      "status": "operational",
      "is_hvdc": false,
      "owner": "LCRA / Oncor",
      "data_source": "HIFLD"
    },
    {
      "id": "branch-oak-grove-gibbons-creek",
      "name": "Oak Grove - Gibbons Creek",
      "from_node_id": "node-oak-grove",
      "to_node_id": "node-gibbons-creek",
      "voltage_kv": 345,
      "capacity_mw": 1200,
      "length_km": 65,
      "status": "operational",
      "is_hvdc": false,
      "owner": "Oncor Electric",
      "data_source": "HIFLD"
    },
    {
      "id": "branch-jones-sweetwater-sub-2",
      "name": "Jones County - Sweetwater Sub (Parallel)",
      "from_node_id": "node-west-texas-jones-county",
      "to_node_id": "node-west-texas-sweetwater-sub",
      "voltage_kv": 345,
      "capacity_mw": 1500,
      "length_km": 58,
      "status": "operational",
      "is_hvdc": false,
      "owner": "Oncor Electric",
      "data_source": "ERCOT CREZ"
    },
    {
      "id": "branch-big-spring-zenith",
      "name": "Big Spring - Zenith (CREZ Central)",
      "from_node_id": "node-west-texas-big-spring",
      "to_node_id": "node-zenith",
      "voltage_kv": 345,
      "capacity_mw": 2400,
      "length_km": 275,
      "status": "operational",
      "is_hvdc": false,
      "owner": "Oncor Electric",
      "data_source": "ERCOT CREZ"
    },
    {
      "id": "branch-lubbock-jones-county",
      "name": "Lubbock - Jones County (CREZ)",
      "from_node_id": "node-west-texas-lubbock",
      "to_node_id": "node-west-texas-jones-county",
      "voltage_kv": 345,
      "capacity_mw": 2000,
      "length_km": 175,
      "status": "operational",
      "is_hvdc": false,
      "owner": "Xcel Energy / Oncor",
      "data_source": "ERCOT CREZ"
    }
  ],
  "summary": {
    "total_branches": 168,
    "voltage_breakdown": {
      "345kV_branches": 157,
      "138kV_branches": 11
    },
    "crez_lines": 18,
    "notes": "Comprehensive transmission network including 345kV backbone triangle (DFW-Houston-San Antonio), CREZ corridors from West Texas and Panhandle, coastal generation connections, and renewable integration lines"
  }
}
